feast/__init__.py
feast/client.py
feast/data_format.py
feast/data_source.py
feast/entity.py
feast/feature.py
feast/feature_table.py
feast/online_response.py
feast/online_store.py
feast/value_type.py
feast/core/CoreService_pb2.py
feast/core/CoreService_pb2.pyi
feast/core/CoreService_pb2_grpc.py
feast/core/DataFormat_pb2.py
feast/core/DataFormat_pb2.pyi
feast/core/DataFormat_pb2_grpc.py
feast/core/DataSource_pb2.py
feast/core/DataSource_pb2.pyi
feast/core/DataSource_pb2_grpc.py
feast/core/Entity_pb2.py
feast/core/Entity_pb2.pyi
feast/core/Entity_pb2_grpc.py
feast/core/FeatureTable_pb2.py
feast/core/FeatureTable_pb2.pyi
feast/core/FeatureTable_pb2_grpc.py
feast/core/Feature_pb2.py
feast/core/Feature_pb2.pyi
feast/core/Feature_pb2_grpc.py
feast/core/LegacyJobService_pb2.py
feast/core/LegacyJobService_pb2.pyi
feast/core/LegacyJobService_pb2_grpc.py
feast/core/OnlineStore_pb2.py
feast/core/OnlineStore_pb2.pyi
feast/core/OnlineStore_pb2_grpc.py
feast/core/SparkOverride_pb2.py
feast/core/SparkOverride_pb2.pyi
feast/core/SparkOverride_pb2_grpc.py
feast/core/__init__.py
feast/gcp/__init__.py
feast/gcp/staging.py
feast/loaders/__init__.py
feast/loaders/file.py
feast/maxcompute/staging.py
feast/serving/ServingService_pb2.py
feast/serving/ServingService_pb2.pyi
feast/serving/ServingService_pb2_grpc.py
feast/serving/__init__.py
feast/types/Field_pb2.py
feast/types/Field_pb2.pyi
feast/types/Field_pb2_grpc.py
feast/types/Value_pb2.py
feast/types/Value_pb2.pyi
feast/types/Value_pb2_grpc.py
feast/types/__init__.py
feast_spark/__init__.py
feast_spark/api/JobService_pb2.py
feast_spark/api/JobService_pb2.pyi
feast_spark/api/JobService_pb2_grpc.py
feast_spark/api/__init__.py
caraml_store-0.4.2.dist-info/METADATA
caraml_store-0.4.2.dist-info/WHEEL
caraml_store-0.4.2.dist-info/top_level.txt
caraml_store-0.4.2.dist-info/RECORD
